{
  "master": {
    "path": "versions/master",
    "name": "master",
    "sha": "06854483f1df88c6c7198894341d878830e5842d",
    "tag": null
  },
  "-latest": {
    "path": "",
    "name": "Latest",
    "sha": "dbde5b41d7212a92155a40f90ddfce42de219e29",
    "tag": "v1.0.0"
  },
  "v1.0.0-rc.2": {
    "path": "versions/v1.0.0-rc.2",
    "name": "v1.0.0-rc.2",
    "sha": "ec1d9339c7aa71d79514781df7cbdb25cc208a96",
    "tag": "v1.0.0-rc.2"
  },
  "v1.0.0-rc.4": {
    "path": "versions/v1.0.0-rc.4",
    "name": "v1.0.0-rc.4",
    "sha": "68f869fcb746a92047f98b0d46165311adfbb9ee",
    "tag": "v1.0.0-rc.4"
  },
  "v1.0.0": {
    "path": "versions/v1.0.0",
    "name": "v1.0.0",
    "sha": "dbde5b41d7212a92155a40f90ddfce42de219e29",
    "tag": "v1.0.0"
  }
}
